{
  "refId": "74209280",
  "name": "Donald Duck ",
  "location": "Alexandria, Virginia, United States",
  "summary": null,
  "profileUrls": [],
  "skills": [
    "IBM WebSphere",
    "MS SQL Server",
    "HP-UX",
    "Apache Webserver",
    "Linux",
    "WAN/LAN",
    "TCP/IP",
    "Java",
    "Sun OS / Solaris",
    "Unix General",
    "SQL",
    "AIX",
    "Asset and Liability Management",
    "Oracle E-Business Suite",
    "Oracle",
    "PL/SQL",
    "MS-Project",
    "MS Sharepoint Portal Server",
    "PMP - Project Management Professional",
    "DevOps",
    "MS Active Directory",
    "Risk Management/Basel II",
    "CMMI",
    "MS Dynamics CRM",
    "RUP - Rational Unified Process",
    "Auditing",
    "Treasury",
    "Change Management",
    "Incident Management",
    "Six Sigma",
    "Citrix",
    "Finance"
  ],
  "experienceEntries": [
    {
      "position": "Senior Program Manager",
      "description": "5/1990 - 5/2000 City of Sebastian- FL Senior Program Manager",
      "custom_company": "City of Sebastian- FL",
      "technologies": [],
      "start_year": 1990,
      "start_month": 5,
      "start_day": 1,
      "end_year": 2000,
      "end_month": 5,
      "end_day": 1
    },
    {
      "position": "Project Manager",
      "description": "Obxtek-- Washington, D.C.\nGovernment Client: US Department of Labor/Office of the Chief Financial Officer (OCFO)\n4/2015 - 3/2018\nIT Program/ Agile Project Manager\nThe project budget was $600 million. The Division of Security and Technology (DST) provides\nInformation Technology related services and support on behalf of the Office of Chief Financial Officer\n(OCFO) of the Department of Labor (DOL). The DST's functional areas are information security; technology support; troubleshooting; infrastructure management; change management; incident management; systems analysis; application development; database administration; executive reporting; A- 123 Audit reviews; enterprise architecture; certification & accreditation; security; continuous monitoring, audit support and tracking; project management; program management, and quality assurance. The DST represents OCFO on various IT-related committees in/out of Department of Labor (DOL). Ensure staff\ncompliance with security protocols in accordance with DOL personnel and administrative policy HIPAA privacy and security and policies procedures manuals. The DST's staff is comprised of information security officers, database administrators, programmers, systems analysts, program management, and other information technology IT-related specialists necessary to the OCFO mission and operations. The\nDST staff supports contractors to develop, implement, and coordinate activities designed to ensure, protect, and restore information technology (IT) infrastructure system services, as well as financial management systems and capabilities. The DST is responsible for executing the government's compliance oversight and control over OCFO systems relating to federal employees group health data, pension data and unemployment benefits to name a few to the US Congress, US Treasury and the DOL. The DST performs quality assurance activities to monitor and remediate technology and security processes within the OCFO. The Division is responsible for communicating enterprise architecture updates to DOL and as well as understanding and communicating architectural issues within OCFO financial systems. The DST provides infrastructure management service for OCFO servers, desktop, laptop, mobile and customer application support. The DST provides expert technical advice and analysis to the Office of the OCFO.\nThe DST provides information security and quality assurance duties for all OCFO IT systems and seeks to meet or exceed federally mandates of the Federal Information Security Management Act, Federal\nInformation System Control Audit, and Office Management and Budget, (OMB Circular A-123), A-130.\nAdditionally, the DST will provide weekly audit dashboards for OCFO across DOL tracking responsible party performance, as well as, develop and maintain monthly dashboard displaying performance metrics.\n - Provides oversight and executive level management to overall contract operations involving multiple projects/tasks and groups of personnel at multiple locations. Maintains and manages relationships with senior executive level management within the client's organization. Responsible for ensuring senior executive level management within the client organization and maintains awareness of overall program status, including all relevant projects and their potential impact on higher level organizational vision, this includes maintaining subject matter expertise and unique technical knowledge. Responsible for managing multiple contract operations, ensure quality standards and work performance on all task orders and projects, plans, organizings and overseeing work efforts, assigns resources, managing personnel, providing risk management, ensureing quality management, monitoring overall project and contract performance, etc.\n - Provided Agile Project Management support in accordance with standards established by Project\nManagement Institute.\n - Conducted multi-project/multi-task technical or A&AS contract assignments\n - Conducted Agile full lifecycles based on a weekly and bi/weekly timeframe.\n - Incorporated Agile planning and reporting throughout the contract tasks as appropriate.\n - Used Agile Project Management for all software development alone with DevOps.\n - Supported New Core Financial Management Suite System (NCFMS) which is a Oracle E-business\nSuite go back to US Congress, US Treasury and the DOL.\n - Implemented SharePoint, Office 365 on (Web services), Cloud promise with tableus for web site for reporting system for Office of the Chief Financial Officer (OCFO) and business intelligence for the\nOCIO and other agency within Department of Labor.\n - Monitored the performance of contract tasks, projects and operational functions notifying government of risk and deviations as they are identified.\n - Created process for Standard Operating Procedure (SOP) document writing, preparing presentations for Senior Executives\n - Implemented process improvements throughout the contract tasks in accordance with findings and recommendation made internally or through external reviews.\n - Planed, managed, and participated technically in any projects or operations within this contract.\n - Organized, directed and coordinated planning and production of all program/project activities.\n - Met with appropriate client management personnel, other managers and client agency representatives.\n - Actively applied quality assurance measures to the management and performance of the program/project.\n - Provided weekly status reporting before the weekly close of business Friday for the week's project and operational work (normally Monday through Friday).\n - Provided dashboards and statistical reports Monday at 8:00 a.m. for the week's project and operational work including totals, process deviations, and policy exceptions (normally Monday through Friday).\n - Supported the Director of Security and Technology Program and Project Management responsibility for all tasks under this contract.\n - Worked with end user groups to evaluate and resolve technical problems.\n - Led strategic planning, budgeting and staffing efforts in response to task requirements\n - Served as point of contact for the CO and the COR\n - Ensured compliance with all administrative and contractual requirements\n - Monitored progress and resolve any issues impacting successful capability delivery.\n - Evaluated existing systems and/or user needs to analyze, design, recommend, and implement system changes.\n - Led team on large projects or significant segment of large infrastructure complex projects.\n - Analyzed new and complex project related problems and creates innovative solutions involving finance, scheduling, technology, methodology, tools, and solution components.\n - Managing IT SDLC and Security projects using agile methodologies.\n - Provided information security experience with asset management (e.g. computer emergency response team or computer network service provider or security operations center, information security program, etc.) at the federal agency.\n - Developed Cybersecurity Assessments on quarterly and annual FISMA inventory filling for OCFO systems for OFS.\n - Developed Cybersecurity Assessments conduct on Annual Privacy Impact Statement for OCFO systems for OFS.\n - Supported the Information Security Office (ISO) or designate with the Division of Security and\nTechnology.\n - Conducting FISMA audits to the Department of Labor on its Audit Readiness/Sustainment engagement; Financial Improvement and Audit Readiness engagements.\n - Assess systems configuration for Federal Financial Management Improvement Act (FFMIA), Federal\nFinancial Management Systems Requirements (FFMSR) compliance.\n - Serve as SME, Financial Systems and overall Federal Government Financial Management processes",
      "custom_company": "Obxtek, D.C.",
      "technologies": [
        "Finance",
        "Change Management",
        "Incident Management",
        "Treasury",
        "Auditing",
        "Risk Management/Basel II",
        "DevOps",
        "Oracle",
        "Oracle E-Business Suite",
        "Asset and Liability Management",
        "C",
        "Web services",
        "dashboards",
        "bi",
        "presentations",
        "SDLC"
      ],
      "start_year": 2015,
      "start_month": 4,
      "start_day": 1,
      "end_year": 2018,
      "end_month": 3,
      "end_day": 1
    },
    {
      "position": "Sr. Project Manager Led",
      "description": "9/2014 - 4/2015\nFreddieMac - Reston, VA\nSr. Project Manager\nLed a variety of projects including launching new services, large-scale infrastructure programs, systems integration, process reengineering, and deployments. Responsible for the planning and execution from start (developing the business case) to finish (project close-out) of Projects. Manage project scope, schedule, budget, quality, risks and issues, impact on systems, and dependencies to other IT Business\nUnits within the organization. Ability to quickly earn the trust of sponsors and key stakeholders; mobilize and motivate teams; set direction and approach; resolved conflict; deliver tough messages with grace; execute with limited information and ambiguity. Ability to communicate at all levels with clarity and precision both written and verbally formats. Maintain extensive knowledge and expertise in the use of\nproject management and SDLC methodologies and tools. Able to navigate through a large corporate environment to ensure appropriate processes are met. Maintain excellent problem-solving and criticalthinking skills. Able to demonstrate, applied experience establishing and delivering complex projects.\nThe project budget was $5Billion.\n - Managed single accountable for defining, planning, orchestrating, and delivering a given initiative.\n - Ensured end results are of the highest caliber with a clearly articulated scope and quantifiable business (i.e. financial) benefit.\n - Use Earned Value Management (EVM) and Critical Path Method (CPM) to ensure integrity and delivery of multiple projects with respect to time, budget, scope, change, risk and resources.\n - Managed with implementation of COTS applications, enterprise tools, and infrastructure projects.\n - Direct large-scale, complex projects often involving multiple internal and external constituents and matrixed partners.\n - Developed for one or more initiatives including business, operational, and IT deliverables.\n - Directly manages all aspects of the project lifecycle and work with matrixed IT infrastructure partners to oversee all SDLC phases or iterations of an Agile project.\n - Rigorously managed scope to ensure commitments are achieved within agreed on time, cost, and quality parameters.\n - Validated financial forecast and provide on-going reconciliation of resources and other related project expenditures.\n - Developed communication plan and effectively communicates in both verbal (e.g. day-to-day discussions, team meetings) and written (status reports, change requests) form.\n - Served as a subject matter expert in routinely briefing key stakeholders on different aspects of assigned initiatives.\n - Ensured that sound practices are taking place. Replace old processes with newer ones where feasible, and provides feedback for efficiencies.\n - Represented the project in various project governance and inter-department forums.\n - Developed the project charter, integrated project plan, resource plan, contingency plan, and related project management artifacts.\n - Managed, define and track project milestones while developing, maintaining, and reporting on an overall integrated delivery plan.\n - Managed and accurately assess risks and issues.\n - Maintained current statements of work for all contractors; track and approve contractor invoices in a timely manner.\n - Provided regular updates to program C-level executive director, project sponsor and stakeholders on the status of the budget and document reasons for budget excess or shortfall.\n - Published periodic project status reports.\n - Proposed recommendations and adjustments.\n - Performed additional job-related duties as requested to get the job done",
      "custom_company": "FreddieMac - Reston, VA",
      "technologies": [
        "Finance",
        "C",
        "SDLC",
        "parameters"
      ],
      "start_year": 2014,
      "start_month": 9,
      "start_day": 1,
      "end_year": 2015,
      "end_month": 4,
      "end_day": 1
    },
    {
      "position": "IT Portfolio Program Manager PMO",
      "description": "10/2008 - 9/2014\nAccenture Federal Service -- Washington, D.C\nUnited States Postal Service (USPS) IT Portfolio Program Manager PMO\nProvide Program Management support for USPS IT Organization. Liaise between USPS customer and IT teams. Excellent written skills to prepare reports/documents for internal presentations, as well as, presentation to various Governance Boards. Advanced planning, organization, analytics and business acumen are required to understand and present the implications of various decisions. Manage the delivery efforts of Managers and Directors, provide leadership, and influence for VP levels and above in the selection and governance of USPS and IT Initiatives.\n - Utilized a comprehensive understanding of corporate strategic imperatives, the long range strategic plan, the full IT Systems Development Lifecycle and the Project Management Life Cycle to ensure compliance with organization goals and timelines. Manage the assignment, development and performance of Project Managers under the program.\n - Managed and responsible for all aspects of the program within a platform initiative fulfillment with budgets up to $60 million, to include risk management, process improvement, and technology applications, development and for enabling the business to meet the future goals and objectives prioritized by the USPS Governance Boards. Support and manage application TSLC/SOX\nCompliance Processes. Functioning of an IT governance PMO office, interacting with executive steering committees and business stakeholders at varying levels.\n - Ensured alignment with the overall USPS Strategic Plan by focusing on compliance, procedures and governance to achieve program goals through the application of a CMMI framework. Communication skills are required to persuade, gain cooperation, provide formal presentations to various sized groups and to reach consensus and resolve conflict.\n - Managed the full project management life cycle and software development life cycle for the implementation of highly complex, large scale, strategic IT infrastructure and Business USPS\ninitiatives within a platform of the long range strategic plan. Acceptance Test Driven Development\n(ATDD), Test Driven Development (TDD), CI/CD and pipeline buildout and optimization\n(specifically using Artemis)\n - Implemented established policies, system monitors and controls to ensure the successful management and reporting of all USPS initiatives in the program.\n - Supervised and lead the program and project staff to oversee the impacts and interdependencies between programs and works to ensure initiatives meet the USPS goals and objectives of the executive leadership team. Perceived by peers and staff as a leader.\n - Managed all aspects of the project/program management of a corporate initiative, which may include: cost benefit analysis, work plans, functional and technical designs, construction, testing and implementation. Ensured efficient and high quality installation of new software and/or systems, and monitors all technical aspects of implementing projects.\n - Developed a comprehensive risk management plan at the program level within the CMMI framework as defined in the USPS processes.\n - Managed and directs multiple medium to large-scale projects that may not fit into a defined program.\n - Managed on complex problems where analysis of situation or data requires an in-depth evaluation of various factors to achieve best results.\n - Translated generalized customer business goals and objectives into concrete strategy and tactical plans.\n - Managed and exercise judgment within broadly defined policies and practices to develop corporate methods and techniques.\n - Worked effectively with internal and external clients, third party vendors, and Senior Management in accomplishing project objectives.\n - Evaluated complex situations accurately and identifies viable solutions that create successful outcomes for the customer.\n - Ensured all USPS defined processes are used within the CMMI Framework and Agile methodology to successfully implement projects.\n - Collaborate with the finance department and various functional managers to ensure project budgets are properly estimated and controlled; provided overall financial recommendations, and developed controls and measurements to monitoring progress.\n - Provided finance with monthly accruals and forecasts by the due date established by Finance using the tools developed by Finance/PMO.\n - Developed and maintained current statements of work for all contractors; tracks and approves contractor invoices in a timely manner.\n - Provided regular updates to Program Director, project sponsor and stakeholders on the status of the budget and document reasons for budget excess or shortfall.\n - Use Earned Value Management (EVM) and Critical Path Method (CPM) to ensure integrity and delivery of multiple projects with respect to time, budget, scope, change, risk and resources.\n - Supervised PMO Sr. Project Managers, Project Managers, Project Coordinators and Budget Analysts; provide performance feedback and goal-setting; conduct annual performance assessments.\n - Developed a comprehensive risk management plan at the program level within the CMMI Framework as defined in the USPS processes.\n - Proactively managed and identified risks and opportunities of both business and technical plans, to identify risk mitigation strategies and contingency plans for all identified risks. Maintain the program level issue and risk matrix log.\n - Provided a detailed plan of how the risk will be managed or eliminated. Provide a weekly program status report Microsoft SharePoint, Microsoft Project, Microsoft Project Server and reporting capabilities with major risk factors when mitigation approach impacted the project timeline, budget, or objectives.\n - Managed and coordinated the risk management plan and risk mitigation strategy across all projects within the program and managed the execution within the individual projects.\n - Supported web content governance. Support web publisher and change control board meetings.\n - Served as a Portfolio Program Manager for USPS.com and Section 508 SME applications.\n - Collaborated with Management Team (IT and Business) and provided advice and guidance on business and program management issues such as roadmap for various USPS.com static and E- Commerce website and Section 508 Applications.\n - Analyzed organizational and operational problems then develop solutions along with assisted\nOperations Support team with the maintaining of the USPS.com site and Section 508 SME.\n - Provided Program Management principle support for the redesign of the new USPS.com website along with Section 508 complaince",
      "custom_company": "Accenture Federal Service",
      "technologies": [
        "CMMI",
        "Risk Management/Basel II",
        "MS Sharepoint Portal Server",
        "MS-Project",
        "C",
        "presentations",
        "CI/CD"
      ],
      "start_year": 2008,
      "start_month": 10,
      "start_day": 1,
      "end_year": 2014,
      "end_month": 9,
      "end_day": 1
    },
    {
      "position": "IT Project Manager",
      "description": "Accentue 6/2008 - 10/2008 Wellcare - Tampa, FL IT Project Manager",
      "custom_company": "Accentue, Wellcare - Tampa, FL",
      "technologies": [],
      "start_year": 2008,
      "start_month": 6,
      "start_day": 1,
      "end_year": 2008,
      "end_month": 10,
      "end_day": 1
    },
    {
      "position": "T/Bellsouth Project Manager",
      "description": "3/ 2006 - 6/2008 Accenture - Atlanta, GA AT&T/Bellsouth Project Manager",
      "custom_company": "Accenture - Atlanta, GA",
      "technologies": [],
      "start_year": 2006,
      "start_month": 3,
      "start_day": 1,
      "end_year": 2008,
      "end_month": 6,
      "end_day": 1
    },
    {
      "position": "Global Payments Oracle Project Manager",
      "description": "12/2005 - 3/2006\nAccenture - Atlanta, GA\nGlobal Payments Oracle Project Manager\nAccenture - Rockville, MD\nFDA Center",
      "custom_company": "Accenture - Atlanta, GA",
      "technologies": [
        "Oracle"
      ],
      "start_year": 2005,
      "start_month": 12,
      "start_day": 1,
      "end_year": 2006,
      "end_month": 3,
      "end_day": 1
    },
    {
      "position": "Program Manager",
      "description": "Program Manager 10/2003-12/2005",
      "custom_company": null,
      "technologies": [],
      "start_year": 2003,
      "start_month": 10,
      "start_day": 1,
      "end_year": 2005,
      "end_month": 12,
      "end_day": 1
    },
    {
      "position": "IT Program Manager",
      "description": "1/2003 -10/2003 State of Georgia Department of Transportation - Atlanta, GA IT Program Manager",
      "custom_company": "State of Georgia Department of Transportation",
      "technologies": [],
      "start_year": 2003,
      "start_month": 1,
      "start_day": 1,
      "end_year": 2003,
      "end_month": 10,
      "end_day": 1
    },
    {
      "position": "DBA/Project Manager",
      "description": "7/2001 - 1/2003\nLinus Technology/Bank of America - Atlanta, GA\nOracle Application DBA/Project Manager",
      "custom_company": "Linus Technology/Bank of America - Atlanta",
      "technologies": [
        "Oracle"
      ],
      "start_year": 2001,
      "start_month": 7,
      "start_day": 1,
      "end_year": 2003,
      "end_month": 1,
      "end_day": 1
    },
    {
      "position": "Lead Project Manager Implementation",
      "description": "5/2000 - 5/2001 MCI/WorldCom -Atlanta, GA Lead Project Manager Implementation",
      "custom_company": "MCI/WorldCom -Atlanta",
      "technologies": [],
      "start_year": 2000,
      "start_month": 5,
      "start_day": 1,
      "end_year": 2001,
      "end_month": 5,
      "end_day": 1
    }
  ],
  "educationEntries": [
    {
      "school_name": "Oracle University",
      "degree": "Certified Implementation Specialist for Oracle Business Intelligence CRM and ERP",
      "discipline": "Database Administration",
      "start_year": 2012,
      "start_month": 1,
      "start_day": 1,
      "end_year": 2017,
      "end_month": 1,
      "end_day": 1
    }
  ],
  "meta": {
    "source": "Jobs page on your website"
  },
  "id": "c753cf2e-87b6-4c34-8e64-35ca20d7d92c",
  "languages": [
    {
      "code": "EN",
      "name": "English",
      "level_code": "C2",
      "level_name": "Perfect or native"
    }
  ],
  "educationLevel": {
    "code": "5A",
    "name": "University education"
  },
  "statistics": [
    {
      "duration": 61,
      "weight": 8,
      "code": "ibmws",
      "name": "IBM WebSphere",
      "domain": "Skill"
    },
    {
      "duration": 98,
      "weight": 30,
      "code": "o",
      "name": "Oracle",
      "domain": "Skill"
    },
    {
      "duration": 61,
      "weight": 49,
      "code": "msad",
      "name": "MS Active Directory",
      "domain": "Skill"
    },
    {
      "duration": 36,
      "weight": 63,
      "code": "treas",
      "name": "Treasury",
      "domain": "Skill"
    },
    {
      "duration": 108,
      "weight": 49,
      "code": "risk",
      "name": "Risk Management/Basel II",
      "domain": "Skill"
    },
    {
      "duration": 61,
      "weight": 8,
      "code": "mssq",
      "name": "MS SQL Server",
      "domain": "Skill"
    },
    {
      "duration": 61,
      "weight": 8,
      "code": "hpux",
      "name": "HP-UX",
      "domain": "Skill"
    },
    {
      "duration": 61,
      "weight": 58,
      "code": "mscrm",
      "name": "MS Dynamics CRM",
      "domain": "Skill"
    },
    {
      "duration": 61,
      "weight": 33,
      "code": "plsql",
      "name": "PL/SQL",
      "domain": "Skill"
    },
    {
      "duration": 75,
      "weight": 83,
      "code": "fin",
      "name": "Finance",
      "domain": "Skill"
    },
    {
      "duration": 72,
      "weight": 34,
      "code": "mspro",
      "name": "MS-Project",
      "domain": "Skill"
    },
    {
      "duration": 36,
      "weight": 68,
      "code": "cm",
      "name": "Change Management",
      "domain": "Skill"
    },
    {
      "duration": 61,
      "weight": 8,
      "code": "apach",
      "name": "Apache Webserver",
      "domain": "Skill"
    },
    {
      "duration": 36,
      "weight": 10,
      "code": "assma",
      "name": "Asset and Liability Management",
      "domain": "Skill"
    },
    {
      "duration": 36,
      "weight": 20,
      "code": "orebs",
      "name": "Oracle E-Business Suite",
      "domain": "Skill"
    },
    {
      "duration": 61,
      "weight": 58,
      "code": "rup",
      "name": "RUP - Rational Unified Process",
      "domain": "Skill"
    },
    {
      "duration": 36,
      "weight": 39,
      "code": "devop",
      "name": "DevOps",
      "domain": "Skill"
    },
    {
      "duration": 36,
      "weight": 58,
      "code": "audit",
      "name": "Auditing",
      "domain": "Skill"
    },
    {
      "duration": 61,
      "weight": 8,
      "code": "lux",
      "name": "Linux",
      "domain": "Skill"
    },
    {
      "duration": 36,
      "weight": 68,
      "code": "im",
      "name": "Incident Management",
      "domain": "Skill"
    },
    {
      "duration": 61,
      "weight": 8,
      "code": "lan",
      "name": "WAN/LAN",
      "domain": "Skill"
    },
    {
      "duration": 61,
      "weight": 8,
      "code": "tcpip",
      "name": "TCP/IP",
      "domain": "Skill"
    },
    {
      "duration": 72,
      "weight": 34,
      "code": "mssp",
      "name": "MS Sharepoint Portal Server",
      "domain": "Skill"
    },
    {
      "duration": 61,
      "weight": 75,
      "code": "sixsi",
      "name": "Six Sigma",
      "domain": "Skill"
    },
    {
      "duration": 61,
      "weight": 75,
      "code": "cit",
      "name": "Citrix",
      "domain": "Skill"
    },
    {
      "duration": 61,
      "weight": 8,
      "code": "j",
      "name": "Java",
      "domain": "Skill"
    },
    {
      "duration": 61,
      "weight": 8,
      "code": "solrs",
      "name": "Sun OS / Solaris",
      "domain": "Skill"
    },
    {
      "duration": 61,
      "weight": 8,
      "code": "unix",
      "name": "Unix General",
      "domain": "Skill"
    },
    {
      "duration": 61,
      "weight": 8,
      "code": "sql",
      "name": "SQL",
      "domain": "Skill"
    },
    {
      "duration": 1,
      "weight": 35,
      "code": "pmp",
      "name": "PMP - Project Management Professional",
      "domain": "Skill"
    },
    {
      "duration": 72,
      "weight": 54,
      "code": "cmmi",
      "name": "CMMI",
      "domain": "Skill"
    },
    {
      "duration": 61,
      "weight": 8,
      "code": "aix",
      "name": "AIX",
      "domain": "Skill"
    },
    {
      "duration": 113,
      "weight": 1,
      "code": "c",
      "name": "C",
      "domain": "Skill"
    },
    {
      "duration": 35,
      "weight": 1,
      "code": "web services",
      "name": "Web services",
      "domain": "Skill"
    },
    {
      "duration": 35,
      "weight": 1,
      "code": "dashboards",
      "name": "dashboards",
      "domain": "Skill"
    },
    {
      "duration": 35,
      "weight": 1,
      "code": "bi",
      "name": "bi",
      "domain": "Skill"
    },
    {
      "duration": 106,
      "weight": 1,
      "code": "presentations",
      "name": "presentations",
      "domain": "Skill"
    },
    {
      "duration": 42,
      "weight": 1,
      "code": "sdlc",
      "name": "SDLC",
      "domain": "Skill"
    },
    {
      "duration": 7,
      "weight": 1,
      "code": "parameters",
      "name": "parameters",
      "domain": "Skill"
    },
    {
      "duration": 71,
      "weight": 1,
      "code": "ci/cd",
      "name": "CI/CD",
      "domain": "Skill"
    },
    {
      "duration": 76,
      "weight": 54,
      "code": "62",
      "name": "Computer programming, consultancy and related activities",
      "domain": "NACE"
    },
    {
      "duration": 91,
      "weight": 55,
      "code": "64",
      "name": "Financial service activities, except insurance and pension funding",
      "domain": "NACE"
    },
    {
      "duration": 299,
      "weight": 62,
      "code": "mgmpl",
      "name": "Project Leader",
      "domain": "Position"
    },
    {
      "duration": 36,
      "weight": 76,
      "code": "mgmgf",
      "name": "Chief Executive Officer (CEO)",
      "domain": "Position"
    },
    {
      "duration": 114,
      "weight": 10,
      "code": "riskm",
      "name": "Risk Management",
      "domain": "OperationArea"
    },
    {
      "duration": 79,
      "weight": 30,
      "code": "bank",
      "name": "Banking",
      "domain": "OperationArea"
    },
    {
      "duration": 108,
      "weight": 49,
      "code": "prod",
      "name": "Product Management",
      "domain": "OperationArea"
    },
    {
      "duration": 36,
      "weight": 10,
      "code": "fabr",
      "name": "Fabrication",
      "domain": "OperationArea"
    },
    {
      "duration": 36,
      "weight": 10,
      "code": "secu",
      "name": "Security Services",
      "domain": "OperationArea"
    },
    {
      "duration": 43,
      "weight": 49,
      "code": "sadm",
      "name": "System Administration",
      "domain": "OperationArea"
    },
    {
      "duration": 36,
      "weight": 10,
      "code": "mare",
      "name": "Market Research",
      "domain": "OperationArea"
    },
    {
      "duration": 61,
      "weight": 12,
      "code": "onlma",
      "name": "Direct Marketing",
      "domain": "OperationArea"
    },
    {
      "duration": 114,
      "weight": 30,
      "code": "sale",
      "name": "Sales/Presale",
      "domain": "OperationArea"
    },
    {
      "duration": 36,
      "weight": 76,
      "code": "offi",
      "name": "Office Management",
      "domain": "OperationArea"
    },
    {
      "duration": 36,
      "weight": 39,
      "code": "admin",
      "name": "Office-Administration",
      "domain": "OperationArea"
    },
    {
      "duration": 61,
      "weight": 12,
      "code": "mark",
      "name": "Marketing",
      "domain": "OperationArea"
    },
    {
      "duration": 108,
      "weight": 49,
      "code": "maint",
      "name": "Application Support",
      "domain": "OperationArea"
    },
    {
      "duration": 36,
      "weight": 49,
      "code": "sysa",
      "name": "System Analysis",
      "domain": "OperationArea"
    },
    {
      "duration": 72,
      "weight": 23,
      "code": "pers",
      "name": "Human Resources",
      "domain": "OperationArea"
    },
    {
      "duration": 114,
      "weight": 49,
      "code": "swe",
      "name": "Software Development",
      "domain": "OperationArea"
    },
    {
      "duration": 36,
      "weight": 30,
      "code": "medas",
      "name": "Medical Assistance",
      "domain": "OperationArea"
    },
    {
      "duration": 108,
      "weight": 30,
      "code": "qm",
      "name": "Quality Management",
      "domain": "OperationArea"
    },
    {
      "duration": 36,
      "weight": 20,
      "code": "nwa",
      "name": "Network Administration",
      "domain": "OperationArea"
    },
    {
      "duration": 36,
      "weight": 30,
      "code": "cust",
      "name": "Customer Service",
      "domain": "OperationArea"
    },
    {
      "duration": 1,
      "weight": 70,
      "code": "sain",
      "name": "Sales Indoor Service",
      "domain": "OperationArea"
    },
    {
      "duration": 43,
      "weight": 30,
      "code": "busan",
      "name": "Business Development",
      "domain": "OperationArea"
    },
    {
      "duration": 72,
      "weight": 54,
      "code": "scm",
      "name": "Supply Chain Management",
      "domain": "OperationArea"
    },
    {
      "duration": 36,
      "weight": 10,
      "code": "event",
      "name": "Event Management",
      "domain": "OperationArea"
    },
    {
      "duration": 100,
      "weight": 29,
      "code": "publ",
      "name": "Publishing Sector",
      "domain": "OperationArea"
    },
    {
      "duration": 43,
      "weight": 10,
      "code": "proce",
      "name": "Process Management",
      "domain": "OperationArea"
    },
    {
      "duration": 51,
      "weight": 79,
      "code": "itman",
      "name": "Head of IT",
      "domain": "OperationArea"
    },
    {
      "duration": 334,
      "weight": 94,
      "code": "pm",
      "name": "Project Management",
      "domain": "OperationArea"
    },
    {
      "duration": 72,
      "weight": 54,
      "code": "ware",
      "name": "Warehousing",
      "domain": "OperationArea"
    },
    {
      "duration": 112,
      "weight": 30,
      "code": "acco",
      "name": "Accountancy",
      "domain": "OperationArea"
    },
    {
      "duration": 72,
      "weight": 54,
      "code": "ana",
      "name": "Business Analysis",
      "domain": "OperationArea"
    },
    {
      "duration": 1,
      "weight": 35,
      "code": "busi",
      "name": "Business Processing",
      "domain": "OperationArea"
    },
    {
      "duration": 36,
      "weight": 30,
      "code": "room",
      "name": "Interior Disign",
      "domain": "OperationArea"
    },
    {
      "duration": 61,
      "weight": 41,
      "code": "dbde",
      "name": "Database Development",
      "domain": "OperationArea"
    },
    {
      "duration": 36,
      "weight": 76,
      "code": "top",
      "name": "",
      "domain": "OperationArea"
    },
    {
      "duration": 91,
      "weight": 17,
      "code": "aadm",
      "name": "Application Administration",
      "domain": "OperationArea"
    },
    {
      "duration": 137,
      "weight": 94,
      "code": "itpm",
      "name": "IT Project Management",
      "domain": "OperationArea"
    },
    {
      "duration": 36,
      "weight": 76,
      "code": "lab",
      "name": "Labor",
      "domain": "OperationArea"
    },
    {
      "duration": 98,
      "weight": 49,
      "code": "dba",
      "name": "Database Administration",
      "domain": "OperationArea"
    },
    {
      "duration": 36,
      "weight": 58,
      "code": "cc",
      "name": "Helpdesk/Technical Support",
      "domain": "OperationArea"
    },
    {
      "duration": 72,
      "weight": 40,
      "code": "plant",
      "name": "Plant Engineering",
      "domain": "OperationArea"
    },
    {
      "duration": 36,
      "weight": 10,
      "code": "audit",
      "name": "Auditing/Assurance",
      "domain": "OperationArea"
    },
    {
      "duration": 36,
      "weight": 39,
      "code": "info",
      "name": "Information Engineering",
      "domain": "OperationArea"
    },
    {
      "duration": 36,
      "weight": 10,
      "code": "aana",
      "name": "Application Analysis",
      "domain": "OperationArea"
    },
    {
      "duration": 214,
      "weight": 99,
      "code": "US",
      "name": "United States",
      "domain": "ISOCountry"
    },
    {
      "duration": 121,
      "weight": 6,
      "code": "AU",
      "name": "Australia",
      "domain": "ISOCountry"
    }
  ],
  "publicActivity": {}
}
